pyprevent-0.1.5.dist-info/METADATA
pyprevent-0.1.5.dist-info/WHEEL
pyprevent-0.1.5.dist-info/license_files/LICENSE.txt
pyprevent/__init__.py
pyprevent/heart_failure.py
pyprevent/utils.py
pyprevent/ascvd_calc.py
pyprevent/cvd.py
pyprevent/_pyprevent.cpython-39-darwin.so
pyprevent-0.1.5.dist-info/RECORD
