Metadata-Version: 2.1
Name: pyprevent
Version: 0.1.5
License-File: LICENSE.txt
Summary: Python implementation of 2024 AHA PREVENT calculator
Author-email: lhegstrom@nference.net
Project-URL: Source, https://github.com/lhegstrom/PyPrevent/
Project-URL: Tracker, https://github.com/lhegstrom/PyPrevent/issues
